pybit_ms/__init__.py
pybit_ms/_exceptions.py
pybit_ms/_http_manager.py
pybit_ms/account.py
pybit_ms/bybit_client.py
pybit_ms/margin.py
pybit_ms/market.py
pybit_ms/trade.py
pybit_ms/data_layer/__init__.py
pybit_ms/data_layer/data_handler.py
pybit_ms-0.1.8.dist-info/LICENSE
pybit_ms-0.1.8.dist-info/METADATA
pybit_ms-0.1.8.dist-info/WHEEL
pybit_ms-0.1.8.dist-info/top_level.txt
pybit_ms-0.1.8.dist-info/RECORD
