Metadata-Version: 2.2
Name: pybit_ms
Version: 0.1.8
Summary: A modification of pybit library to facilitate trading automation and analysis.
Home-page: https://github.com/SamueleMancini/pybit_ms
Author: Michelangelo Nardi and Samuele Mancini
Author-email: nardimichelangelo@gmail.com, samuelemancini96@gmail.com
License: MIT
Classifier: Programming Language :: Python :: 3
Classifier: License :: OSI Approved :: MIT License
Classifier: Operating System :: OS Independent
Requires-Python: >=3.12
License-File: LICENSE
Requires-Dist: requests
Requires-Dist: pycryptodome
Requires-Dist: matplotlib
Requires-Dist: pandas
Requires-Dist: ipython
Dynamic: author
Dynamic: author-email
Dynamic: classifier
Dynamic: description
Dynamic: description-content-type
Dynamic: home-page
Dynamic: license
Dynamic: requires-dist
Dynamic: requires-python
Dynamic: summary
